polint.py
polint-0.5.dist-info/licenses/LICENSE
polint-0.5.dist-info/METADATA
polint-0.5.dist-info/WHEEL
polint-0.5.dist-info/entry_points.txt
polint-0.5.dist-info/top_level.txt
polint-0.5.dist-info/RECORD
