Metadata-Version: 2.4
Name: polint
Version: 0.5
Summary: Linter for gettext PO files
Home-page: https://github.com/ziima/polint
Author: Vlastimil Zíma
Author-email: vlastimil.zima@gmail.com
License: GPLv3+
Keywords: gettext,linter
Platform: any
Classifier: Development Status :: 5 - Production/Stable
Classifier: Environment :: Console
Classifier: Intended Audience :: Developers
Classifier: License :: OSI Approved :: GNU General Public License v3 or later (GPLv3+)
Classifier: Natural Language :: English
Classifier: Operating System :: OS Independent
Classifier: Programming Language :: Python
Classifier: Programming Language :: Python :: 3
Classifier: Programming Language :: Python :: 3.9
Classifier: Programming Language :: Python :: 3.10
Classifier: Programming Language :: Python :: 3.11
Classifier: Programming Language :: Python :: 3.12
Classifier: Programming Language :: Python :: 3.13
Classifier: Topic :: Software Development :: Build Tools
Classifier: Topic :: Software Development :: Internationalization
Classifier: Topic :: Software Development :: Quality Assurance
Classifier: Topic :: Utilities
Requires-Python: ~=3.9
License-File: LICENSE
Requires-Dist: docopt
Requires-Dist: polib
Provides-Extra: quality
Requires-Dist: flake8; extra == "quality"
Requires-Dist: isort; extra == "quality"
Requires-Dist: pydocstyle; extra == "quality"
Provides-Extra: tests
Requires-Dist: mock; extra == "tests"
Dynamic: author
Dynamic: license-file
